gamedetector/__init__.py
gamedetector/app_exes.json
gamedetector/game_detect.py
gamedetector-0.2.3.dist-info/LICENSE
gamedetector-0.2.3.dist-info/METADATA
gamedetector-0.2.3.dist-info/WHEEL
gamedetector-0.2.3.dist-info/RECORD
