Metadata-Version: 2.1
Name: gamedetector
Version: 0.2.3
Summary: The GameDetector library allows you to detect a game within a folder, returning information like Steam AppId, game name, and version.
License: MIT
Author: Aareon Sullivan
Author-email: askully13@gmail.com
Requires-Python: >=3.10,<4.0
Classifier: License :: OSI Approved :: MIT License
Classifier: Programming Language :: Python :: 3
Classifier: Programming Language :: Python :: 3.10
Classifier: Programming Language :: Python :: 3.11
Requires-Dist: beautifulsoup4 (>=4.12.2,<5.0.0)
Requires-Dist: detect-delimiter (>=0.1.1,<0.2.0)
Requires-Dist: fuzzysearch (>=0.7.3,<0.8.0)
Requires-Dist: py7zr (>=0.20.5,<0.21.0)
Requires-Dist: ratelimit (>=2.2.1,<3.0.0)
Requires-Dist: requests (>=2.31.0,<3.0.0)
Requires-Dist: ujson (>=5.7.0,<6.0.0)
